fdev_ids/__init__.py
fdev_ids/_loader.py
fdev_ids/FDevIDs/CQCRank.csv
fdev_ids/FDevIDs/EmpireRank.csv
fdev_ids/FDevIDs/ExplorationRank.csv
fdev_ids/FDevIDs/FederationRank.csv
fdev_ids/FDevIDs/TradeRank.csv
fdev_ids/FDevIDs/bundles.csv
fdev_ids/FDevIDs/combatrank.csv
fdev_ids/FDevIDs/commodity.csv
fdev_ids/FDevIDs/crimes.csv
fdev_ids/FDevIDs/dockingdeniedreasons.csv
fdev_ids/FDevIDs/economy.csv
fdev_ids/FDevIDs/engineers.csv
fdev_ids/FDevIDs/factionids.csv
fdev_ids/FDevIDs/factionstate.csv
fdev_ids/FDevIDs/government.csv
fdev_ids/FDevIDs/happiness.csv
fdev_ids/FDevIDs/material.csv
fdev_ids/FDevIDs/microresources.csv
fdev_ids/FDevIDs/outfitting.csv
fdev_ids/FDevIDs/passengers.csv
fdev_ids/FDevIDs/rare_commodity.csv
fdev_ids/FDevIDs/rings.csv
fdev_ids/FDevIDs/security.csv
fdev_ids/FDevIDs/shipyard.csv
fdev_ids/FDevIDs/sku.csv
fdev_ids/FDevIDs/systemallegiance.csv
fdev_ids/FDevIDs/terraformingstate.csv
fdev_ids-1.1.0.dist-info/licenses/LICENSE
fdev_ids-1.1.0.dist-info/METADATA
fdev_ids-1.1.0.dist-info/WHEEL
fdev_ids-1.1.0.dist-info/top_level.txt
fdev_ids-1.1.0.dist-info/RECORD
