Metadata-Version: 2.4
Name: fdev-ids
Version: 1.1.0
Summary: Data from https://github.com/EDCD/FDevIDs bundled in Python data structures.
Author: Julien de la Bruère-Terreault
Maintainer: Julien de la Bruère-Terreault
License-Expression: MIT
Project-URL: Homepage, https://codeberg.org/jdlbt/fdev-ids-python
Project-URL: Issue tracker, https://codeberg.org/jdlbt/fdev-ids-python/issues
Project-URL: Source, https://codeberg.org/jdlbt/fdev-ids-python
Classifier: Development Status :: 5 - Production/Stable
Classifier: Intended Audience :: Developers
Classifier: Programming Language :: Python
Classifier: Programming Language :: Python :: 3 :: Only
Classifier: Programming Language :: Python :: 3.10
Classifier: Programming Language :: Python :: 3.11
Classifier: Programming Language :: Python :: 3.12
Classifier: Programming Language :: Python :: 3.13
Classifier: Programming Language :: Python :: 3.14
Requires-Python: >=3.10
License-File: LICENSE
Provides-Extra: tests
Requires-Dist: pytest; extra == "tests"
Requires-Dist: pytest-cov; extra == "tests"
Requires-Dist: pytest-regressions; extra == "tests"
Provides-Extra: dev
Requires-Dist: fdev-ids[tests]; extra == "dev"
Requires-Dist: black==25.9.0; extra == "dev"
Requires-Dist: build; extra == "dev"
Requires-Dist: flake8==7.3.0; extra == "dev"
Requires-Dist: isort==6.1.0; extra == "dev"
Requires-Dist: pre-commit; extra == "dev"
Requires-Dist: tox; extra == "dev"
Dynamic: license-file
